.coveragerc
.flake8
.gitignore
.gitmodules
.isort.cfg
.markdown-lint.yml
.pre-commit-config.yaml
BUILD_TIMELORD.md
CHANGELOG.md
CODE_OF_CONDUCT.md
CONTRIBUTING.md
INSTALL.md
Install-gui.ps1
Install-plotter.ps1
Install.ps1
LICENSE
README.md
activated.ps1
activated.py
activated.sh
install-gui.sh
install-plotter.sh
install-timelord.sh
install.sh
installhelper.py
lgtm.yml
mypy.ini
pylintrc
pyproject.toml
pytest.ini
run-py-tests.sh
setup.py
start-gui.sh
.github/CODEOWNERS
.github/dependabot.yml
.github/ISSUE_TEMPLATE/bug_report.yaml
.github/ISSUE_TEMPLATE/config.yml
.github/actions/install/action.yml
.github/workflows/build-linux-installer-deb.yml
.github/workflows/build-linux-installer-rpm.yml
.github/workflows/build-macos-installers.yml
.github/workflows/build-windows-installer.yml
.github/workflows/check_wheel_availability.yaml
.github/workflows/codeql-analysis.yml
.github/workflows/conflict-check.yml
.github/workflows/dependency-review.yml
.github/workflows/mozilla-ca-cert.yml
.github/workflows/super-linter.yml
.github/workflows/upload-pypi-source.yml
.github/workflows.disabled/benchmarks.yml
.github/workflows.disabled/build-linux-arm64-installer.yml
.github/workflows.disabled/pre-commit.yml
.github/workflows.disabled/stale-issue.yml
.github/workflows.disabled/start-release.yml
.github/workflows.disabled/test-install-scripts.yml
.github/workflows.disabled/test-single.yml
.github/workflows.disabled/test.yml
.github/workflows.disabled/trigger-docker-dev.yml
.github/workflows.disabled/trigger-docker-main.yml
benchmarks/__init__.py
benchmarks/block_ref.py
benchmarks/block_store.py
benchmarks/clvm_generator.bin
benchmarks/coin_store.py
benchmarks/jsonify.py
benchmarks/mempool.py
benchmarks/streamable.py
benchmarks/transaction_height_delta
benchmarks/utils.py
build_scripts/__init__.py
build_scripts/build_linux_deb-1-gui.sh
build_scripts/build_linux_deb-2-installer.sh
build_scripts/build_linux_rpm-1-gui.sh
build_scripts/build_linux_rpm-2-installer.sh
chinilla_blockchain.egg-info/PKG-INFO
chinilla_blockchain.egg-info/SOURCES.txt
chinilla_blockchain.egg-info/dependency_links.txt
chinilla_blockchain.egg-info/entry_points.txt
chinilla_blockchain.egg-info/not-zip-safe
chinilla_blockchain.egg-info/requires.txt
chinilla_blockchain.egg-info/top_level.txt
