Metadata-Version: 2.1
Name: chinilla-blockchain
Version: 1.3.1
Summary: Chinilla blockchain full node, farmer, timelord, and wallet.
Home-page: https://chinilla.com/
Author: Mariano Sorgente
Author-email: mariano@chinilla.com
License: Apache License
Project-URL: Source, https://github.com/Chinilla/chinilla-blockchain/
Project-URL: Changelog, https://github.com/Chinilla/chinilla-blockchain/blob/main/CHANGELOG.md
Keywords: chinilla blockchain node
Requires-Python: >=3.7, <4
Provides-Extra: uvloop
Provides-Extra: dev
Provides-Extra: upnp
License-File: LICENSE
